MANIFEST.in
README.md
setup.cfg
setup.py
pypi_up/__about__.py
pypi_up/__about__.pyc
pypi_up/__init__.py
pypi_up/__init__.pyc
pypi_up.egg-info/PKG-INFO
pypi_up.egg-info/SOURCES.txt
pypi_up.egg-info/dependency_links.txt
pypi_up.egg-info/entry_points.txt
pypi_up.egg-info/not-zip-safe
pypi_up.egg-info/requires.txt
pypi_up.egg-info/top_level.txt