Metadata-Version: 1.1
Name: pypi-up
Version: 0.3.2
Summary: pypi-up a simple command line tool to increase version number of package and release it on Pypi
Home-page: https://github.com/mardix/pypi-up
Author: Mardix
Author-email: mardix@pylot.io
License: MIT
Keywords: reversionup
Platform: any
Classifier: Environment :: Web Environment
Classifier: Intended Audience :: Developers
Classifier: License :: OSI Approved :: BSD License
Classifier: Operating System :: OS Independent
Classifier: Programming Language :: Python
Classifier: Programming Language :: Python :: 2
Classifier: Programming Language :: Python :: 2.6
Classifier: Programming Language :: Python :: 2.7
Classifier: Programming Language :: Python :: 3
Classifier: Programming Language :: Python :: 3.3
Classifier: Programming Language :: Python :: 3.4
Classifier: Topic :: Internet :: WWW/HTTP :: Dynamic Content
Classifier: Topic :: Software Development :: Libraries :: Python Modules
